{
  "_class": "symbolInstance",
  "do_objectID": "653599E7-68AA-4F72-ABFA-1D57372E2AA6",
  "exportOptions": {
    "_class": "exportOptions",
    "exportFormats": [
    ],
    "includedLayerIds": [
    ],
    "layerOptions": 0,
    "shouldTrim": false
  },
  "frame": {
    "_class": "rect",
    "constrainProportions": false,
    "height": 121.5921054141028,
    "width": 243.9885806583634,
    "x": 567,
    "y": 11
  },
  "horizontalSpacing": 0,
  "isFlippedHorizontal": false,
  "isFlippedVertical": true,
  "isLocked": false,
  "isVisible": true,
  "layerListExpandedType": 0,
  "masterInfluenceEdgeMaxXPadding": 9,
  "masterInfluenceEdgeMaxYPadding": 9,
  "masterInfluenceEdgeMinXPadding": 9,
  "masterInfluenceEdgeMinYPadding": 9,
  "name": "Nuvola",
  "nameIsFixed": false,
  "overrideValues": [
  ],
  "overrides": {
  },
  "resizingConstraint": 63,
  "resizingType": 0,
  "rotation": 0,
  "scale": 1,
  "shouldBreakMaskChain": false,
  "style": {
    "_class": "style",
    "endDecorationType": 0,
    "miterLimit": 10,
    "startDecorationType": 0
  },
  "symbolID": "C8197652-2A4E-4167-A5EA-C40FC8AC8A1B",
  "verticalSpacing": 0
}